maysics/__init__.py
maysics/calc.py
maysics/digital.py
maysics/equa.py
maysics/explain.py
maysics/graph.py
maysics/models.py
maysics/prep.py
maysics/stats.py
maysics/time.py
maysics/trans.py
maysics/utils.py
maysics-0.5.4.dist-info/LICENSE.txt
maysics-0.5.4.dist-info/METADATA
maysics-0.5.4.dist-info/WHEEL
maysics-0.5.4.dist-info/top_level.txt
maysics-0.5.4.dist-info/RECORD
