Metadata-Version: 2.1
Name: maysics
Version: 0.5.4
Summary: A framework for calculating and modeling
Home-page: https://github.com/HOKOTATE-pzw/maysics.git
Author: HOKOTATE
Author-email: pangzewei2010@foxmail.com
License: MIT
Platform: UNKNOWN
Classifier: License :: OSI Approved :: MIT License
Classifier: Programming Language :: Python
Classifier: Programming Language :: Python :: 3
Classifier: Programming Language :: Python :: 3.10
Classifier: Programming Language :: Python :: Implementation :: CPython
Classifier: Programming Language :: Python :: Implementation :: PyPy
Requires-Python: >=3.6.0
License-File: LICENSE.txt
Requires-Dist: matplotlib
Requires-Dist: numpy
Requires-Dist: scipy (>=1.3.0)
Requires-Dist: lxml
